agent_lib/__init__.py
agent_lib/core/__init__.py
agent_lib/core/agent_block.py
agent_lib/core/conditional_step.py
agent_lib/core/event_emitter.py
agent_lib/core/execution_context.py
agent_lib/core/flow.py
agent_lib/core/flow_adapter.py
agent_lib/events/__init__.py
agent_lib/events/event_models.py
agent_lib/events/adapters/__init__.py
agent_lib/events/adapters/metrics.py
agent_lib/events/adapters/structured_logging.py
agent_lib/events/adapters/webhook.py
agent_lib/integrations/__init__.py
agent_lib/retry/__init__.py
agent_lib/retry/llm_fallback_retry.py
agent_lib/retry/retry_strategy.py
agent_lib/testing/__init__.py
agent_lib/testing/assertions.py
agent_lib/testing/fixtures.py
agent_lib/testing/mock_agents.py
agent_lib/utils/__init__.py
agent_lib/utils/data_transform.py
agent_lib/utils/validation.py
agent_orchestration_lib-0.2.1.dist-info/METADATA
agent_orchestration_lib-0.2.1.dist-info/WHEEL
agent_orchestration_lib-0.2.1.dist-info/licenses/LICENSE
agent_orchestration_lib-0.2.1.dist-info/RECORD
