Metadata-Version: 2.4
Name: agent-orchestration-lib
Version: 0.2.1
Summary: A framework for building composable, observable, and maintainable agent workflows
Project-URL: Homepage, https://github.com/GittieLabs/agent-orchestration-lib
Project-URL: Documentation, https://agent-orchestration-lib.readthedocs.io
Project-URL: Repository, https://github.com/GittieLabs/agent-orchestration-lib
Project-URL: Issues, https://github.com/GittieLabs/agent-orchestration-lib/issues
Author-email: Keith Elliott <keith@gittie.co>
License: MIT
License-File: LICENSE
Keywords: agents,ai,llm,orchestration,workflow
Classifier: Development Status :: 3 - Alpha
Classifier: Intended Audience :: Developers
Classifier: License :: OSI Approved :: MIT License
Classifier: Programming Language :: Python :: 3.10
Classifier: Programming Language :: Python :: 3.11
Classifier: Programming Language :: Python :: 3.12
Classifier: Topic :: Software Development :: Libraries :: Python Modules
Requires-Python: >=3.10
Requires-Dist: loguru>=0.7.0
Requires-Dist: pydantic>=2.0.0
Provides-Extra: all
Requires-Dist: httpx>=0.24.0; extra == 'all'
Provides-Extra: dev
Requires-Dist: black>=23.0.0; extra == 'dev'
Requires-Dist: mkdocs-material>=9.4.0; extra == 'dev'
Requires-Dist: mkdocs>=1.5.0; extra == 'dev'
Requires-Dist: mkdocstrings[python]>=0.24.0; extra == 'dev'
Requires-Dist: mypy>=1.5.0; extra == 'dev'
Requires-Dist: pytest-asyncio>=0.21.0; extra == 'dev'
Requires-Dist: pytest-cov>=4.1.0; extra == 'dev'
Requires-Dist: pytest>=7.4.0; extra == 'dev'
Requires-Dist: ruff>=0.1.0; extra == 'dev'
Provides-Extra: webhooks
Requires-Dist: httpx>=0.24.0; extra == 'webhooks'
